oopzchool
