Metadata-Version: 2.1
Name: oopzchool
Version: 0.0.2
Summary: OOPzchool learning to upload to PyPI
Home-page: https://github.com/Tun555/zchool
Author: Tun Kedsaro
Author-email: Tun.k@ku.th
License: MIT
Download-URL: https://github.com/Tun555/zchool/archive/refs/tags/v0.0.2.zipp
Keywords: OOP,zhcool,Tun
Platform: UNKNOWN
Classifier: Development Status :: 3 - Alpha
Classifier: Intended Audience :: Developers
Classifier: Topic :: Software Development :: Build Tools
Classifier: License :: OSI Approved :: MIT License
Classifier: Programming Language :: Python :: 3
Classifier: Programming Language :: Python :: 3.4
Classifier: Programming Language :: Python :: 3.5
Classifier: Programming Language :: Python :: 3.6
Classifier: Programming Language :: Python :: 3.7
Classifier: Programming Language :: Python :: 3.8
Classifier: Programming Language :: Python :: 3.9
License-File: LICENSE
License-File: LICENSE.txt
